[{"df":3,"postings":"data/search/postings/q4.json","token":"q-4"},{"df":3,"postings":"data/search/postings/q4.json","token":"q-40"},{"df":3,"postings":"data/search/postings/q4.json","token":"q-41"},{"df":3,"postings":"data/search/postings/q4.json","token":"q-42"},{"df":3,"postings":"data/search/postings/q4.json","token":"q-43"},{"df":3,"postings":"data/search/postings/q4.json","token":"q-44"},{"df":3,"postings":"data/search/postings/q4.json","token":"q-449"},{"df":3,"postings":"data/search/postings/q4.json","token":"q-45"},{"df":3,"postings":"data/search/postings/q4.json","token":"q-46"},{"df":3,"postings":"data/search/postings/q4.json","token":"q-47"},{"df":3,"postings":"data/search/postings/q4.json","token":"q-48"},{"df":3,"postings":"data/search/postings/q4.json","token":"q-49"},{"df":3,"postings":"data/search/postings/q4.json","token":"q4"},{"df":1,"postings":"data/search/postings/q4.json","token":"q_4.pdf"},{"df":1,"postings":"data/search/postings/q4.json","token":"q_40.pdf"},{"df":1,"postings":"data/search/postings/q4.json","token":"q_41.pdf"},{"df":1,"postings":"data/search/postings/q4.json","token":"q_42.pdf"},{"df":1,"postings":"data/search/postings/q4.json","token":"q_43.pdf"},{"df":1,"postings":"data/search/postings/q4.json","token":"q_44.pdf"},{"df":1,"postings":"data/search/postings/q4.json","token":"q_449.pdf"},{"df":1,"postings":"data/search/postings/q4.json","token":"q_45.pdf"},{"df":1,"postings":"data/search/postings/q4.json","token":"q_46.pdf"},{"df":1,"postings":"data/search/postings/q4.json","token":"q_47.pdf"},{"df":1,"postings":"data/search/postings/q4.json","token":"q_48.pdf"},{"df":1,"postings":"data/search/postings/q4.json","token":"q_49.pdf"}]
