[{"df":1,"postings":"data/search/postings/sn.json","token":"snac"},{"df":9,"postings":"data/search/postings/sn.json","token":"snapshot"},{"df":4,"postings":"data/search/postings/sn.json","token":"snapshots"},{"df":2,"postings":"data/search/postings/sn.json","token":"snci"},{"df":1,"postings":"data/search/postings/sn.json","token":"sncis"},{"df":1,"postings":"data/search/postings/sn.json","token":"sncrs"},{"df":1,"postings":"data/search/postings/sn.json","token":"snh"},{"df":1,"postings":"data/search/postings/sn.json","token":"snomed-ct"},{"df":10,"postings":"data/search/postings/sn.json","token":"sns"},{"df":1,"postings":"data/search/postings/sn.json","token":"sns.pdf"},{"df":1,"postings":"data/search/postings/sn.json","token":"sns_arcgis.zip"},{"df":1,"postings":"data/search/postings/sn.json","token":"sns_os.zip"}]
