{"fla":[{"df":94,"token":"flat"},{"df":4,"token":"flats"},{"df":2,"token":"flamborough"},{"df":1,"token":"flag"},{"df":1,"token":"flamborough-head-csac-intertidal-biotope-map"},{"df":1,"token":"flareeppermits"},{"df":1,"token":"flask"}],"flag":[{"df":1,"token":"flag"}],"flam":[{"df":2,"token":"flamborough"},{"df":1,"token":"flamborough-head-csac-intertidal-biotope-map"}],"flamb":[{"df":2,"token":"flamborough"},{"df":1,"token":"flamborough-head-csac-intertidal-biotope-map"}],"flambo":[{"df":2,"token":"flamborough"},{"df":1,"token":"flamborough-head-csac-intertidal-biotope-map"}],"flambor":[{"df":2,"token":"flamborough"},{"df":1,"token":"flamborough-head-csac-intertidal-biotope-map"}],"flamboro":[{"df":2,"token":"flamborough"},{"df":1,"token":"flamborough-head-csac-intertidal-biotope-map"}],"flar":[{"df":1,"token":"flareeppermits"}],"flare":[{"df":1,"token":"flareeppermits"}],"flaree":[{"df":1,"token":"flareeppermits"}],"flareep":[{"df":1,"token":"flareeppermits"}],"flareepp":[{"df":1,"token":"flareeppermits"}],"flas":[{"df":1,"token":"flask"}],"flask":[{"df":1,"token":"flask"}],"flat":[{"df":94,"token":"flat"},{"df":4,"token":"flats"}],"flats":[{"df":4,"token":"flats"}],"fle":[{"df":6,"token":"flexibly"},{"df":3,"token":"fleetlands"},{"df":2,"token":"fleets"},{"df":1,"token":"flexible"}],"flee":[{"df":3,"token":"fleetlands"},{"df":2,"token":"fleets"}],"fleet":[{"df":3,"token":"fleetlands"},{"df":2,"token":"fleets"}],"fleetl":[{"df":3,"token":"fleetlands"}],"fleetla":[{"df":3,"token":"fleetlands"}],"fleetlan":[{"df":3,"token":"fleetlands"}],"fleets":[{"df":2,"token":"fleets"}],"flex":[{"df":6,"token":"flexibly"},{"df":1,"token":"flexible"}],"flexi":[{"df":6,"token":"flexibly"},{"df":1,"token":"flexible"}],"flexib":[{"df":6,"token":"flexibly"},{"df":1,"token":"flexible"}],"flexibl":[{"df":6,"token":"flexibly"},{"df":1,"token":"flexible"}],"flexible":[{"df":1,"token":"flexible"}],"flexibly":[{"df":6,"token":"flexibly"}],"flo":[{"df":64,"token":"flood"},{"df":49,"token":"flooding"},{"df":20,"token":"flow"},{"df":8,"token":"floor"},{"df":7,"token":"floodrisk"},{"df":5,"token":"flood-zones"},{"df":4,"token":"flood-monitoring"},{"df":3,"token":"flood-risk-areas1"},{"df":3,"token":"flood-risk-assets1"},{"df":3,"token":"flood-warning-areas2"},{"df":3,"token":"floodzone"},{"df":2,"token":"flood_strategy_area"},{"df":2,"token":"floods"},{"df":2,"token":"flora_tpo_merged"},{"df":1,"token":"floodplain"},{"df":1,"token":"flowers"}],"floo":[{"df":64,"token":"flood"},{"df":49,"token":"flooding"},{"df":8,"token":"floor"},{"df":7,"token":"floodrisk"},{"df":5,"token":"flood-zones"},{"df":4,"token":"flood-monitoring"},{"df":3,"token":"flood-risk-areas1"},{"df":3,"token":"flood-risk-assets1"},{"df":3,"token":"flood-warning-areas2"},{"df":3,"token":"floodzone"},{"df":2,"token":"flood_strategy_area"},{"df":2,"token":"floods"},{"df":1,"token":"floodplain"}],"flood":[{"df":64,"token":"flood"},{"df":49,"token":"flooding"},{"df":7,"token":"floodrisk"},{"df":5,"token":"flood-zones"},{"df":4,"token":"flood-monitoring"},{"df":3,"token":"flood-risk-areas1"},{"df":3,"token":"flood-risk-assets1"},{"df":3,"token":"flood-warning-areas2"},{"df":3,"token":"floodzone"},{"df":2,"token":"flood_strategy_area"},{"df":2,"token":"floods"},{"df":1,"token":"floodplain"}],"flood-":[{"df":5,"token":"flood-zones"},{"df":4,"token":"flood-monitoring"},{"df":3,"token":"flood-risk-areas1"},{"df":3,"token":"flood-risk-assets1"},{"df":3,"token":"flood-warning-areas2"}],"flood-m":[{"df":4,"token":"flood-monitoring"}],"flood-mo":[{"df":4,"token":"flood-monitoring"}],"flood-r":[{"df":3,"token":"flood-risk-areas1"},{"df":3,"token":"flood-risk-assets1"}],"flood-ri":[{"df":3,"token":"flood-risk-areas1"},{"df":3,"token":"flood-risk-assets1"}],"flood-w":[{"df":3,"token":"flood-warning-areas2"}],"flood-wa":[{"df":3,"token":"flood-warning-areas2"}],"flood-z":[{"df":5,"token":"flood-zones"}],"flood-zo":[{"df":5,"token":"flood-zones"}],"flood_":[{"df":2,"token":"flood_strategy_area"}],"flood_s":[{"df":2,"token":"flood_strategy_area"}],"flood_st":[{"df":2,"token":"flood_strategy_area"}],"floodi":[{"df":49,"token":"flooding"}],"floodin":[{"df":49,"token":"flooding"}],"flooding":[{"df":49,"token":"flooding"}],"floodp":[{"df":1,"token":"floodplain"}],"floodpl":[{"df":1,"token":"floodplain"}],"floodpla":[{"df":1,"token":"floodplain"}],"floodr":[{"df":7,"token":"floodrisk"}],"floodri":[{"df":7,"token":"floodrisk"}],"floodris":[{"df":7,"token":"floodrisk"}],"floods":[{"df":2,"token":"floods"}],"floodz":[{"df":3,"token":"floodzone"}],"floodzo":[{"df":3,"token":"floodzone"}],"floodzon":[{"df":3,"token":"floodzone"}],"floor":[{"df":8,"token":"floor"}],"flor":[{"df":2,"token":"flora_tpo_merged"}],"flora":[{"df":2,"token":"flora_tpo_merged"}],"flora_":[{"df":2,"token":"flora_tpo_merged"}],"flora_t":[{"df":2,"token":"flora_tpo_merged"}],"flora_tp":[{"df":2,"token":"flora_tpo_merged"}],"flow":[{"df":20,"token":"flow"},{"df":1,"token":"flowers"},{"df":1,"token":"flows"}],"flowe":[{"df":1,"token":"flowers"}],"flower":[{"df":1,"token":"flowers"}],"flowers":[{"df":1,"token":"flowers"}],"flows":[{"df":1,"token":"flows"}],"flu":[{"df":1,"token":"flu"}],"fly":[{"df":1,"token":"flying"}],"flyi":[{"df":1,"token":"flying"}],"flyin":[{"df":1,"token":"flying"}],"flying":[{"df":1,"token":"flying"}]}
