{"rbb":[{"df":5,"token":"rbbc-inspire-service"}],"rbbc":[{"df":5,"token":"rbbc-inspire-service"}],"rbbc-":[{"df":5,"token":"rbbc-inspire-service"}],"rbbc-i":[{"df":5,"token":"rbbc-inspire-service"}],"rbbc-in":[{"df":5,"token":"rbbc-inspire-service"}],"rbbc-ins":[{"df":5,"token":"rbbc-inspire-service"}],"rbc":[{"df":4,"token":"rbc"},{"df":3,"token":"rbc-air-quality-management-areas"},{"df":3,"token":"rbc-brownfield-register1"},{"df":3,"token":"rbc-green-belt2"},{"df":3,"token":"rbc-tree-preservation-orders1"}],"rbc-":[{"df":3,"token":"rbc-air-quality-management-areas"},{"df":3,"token":"rbc-brownfield-register1"},{"df":3,"token":"rbc-green-belt2"},{"df":3,"token":"rbc-tree-preservation-orders1"}],"rbc-a":[{"df":3,"token":"rbc-air-quality-management-areas"}],"rbc-ai":[{"df":3,"token":"rbc-air-quality-management-areas"}],"rbc-air":[{"df":3,"token":"rbc-air-quality-management-areas"}],"rbc-air-":[{"df":3,"token":"rbc-air-quality-management-areas"}],"rbc-b":[{"df":3,"token":"rbc-brownfield-register1"}],"rbc-br":[{"df":3,"token":"rbc-brownfield-register1"}],"rbc-bro":[{"df":3,"token":"rbc-brownfield-register1"}],"rbc-brow":[{"df":3,"token":"rbc-brownfield-register1"}],"rbc-g":[{"df":3,"token":"rbc-green-belt2"}],"rbc-gr":[{"df":3,"token":"rbc-green-belt2"}],"rbc-gre":[{"df":3,"token":"rbc-green-belt2"}],"rbc-gree":[{"df":3,"token":"rbc-green-belt2"}],"rbc-t":[{"df":3,"token":"rbc-tree-preservation-orders1"}],"rbc-tr":[{"df":3,"token":"rbc-tree-preservation-orders1"}],"rbc-tre":[{"df":3,"token":"rbc-tree-preservation-orders1"}],"rbc-tree":[{"df":3,"token":"rbc-tree-preservation-orders1"}],"rbw":[{"df":19,"token":"rbwm"},{"df":3,"token":"rbwm-settlements"},{"df":1,"token":"rbwm-allotments"},{"df":1,"token":"rbwm-conservation-areas"},{"df":1,"token":"rbwm-employment-sites"},{"df":1,"token":"rbwm-new-housing-sites"},{"df":1,"token":"rbwm-owned-open-spaces"},{"df":1,"token":"rbwm-potential-development-sites"},{"df":1,"token":"rbwm-smoke-control-zones"},{"df":1,"token":"rbwm-village-greens"}],"rbwm":[{"df":19,"token":"rbwm"},{"df":3,"token":"rbwm-settlements"},{"df":1,"token":"rbwm-allotments"},{"df":1,"token":"rbwm-conservation-areas"},{"df":1,"token":"rbwm-employment-sites"},{"df":1,"token":"rbwm-new-housing-sites"},{"df":1,"token":"rbwm-owned-open-spaces"},{"df":1,"token":"rbwm-potential-development-sites"},{"df":1,"token":"rbwm-smoke-control-zones"},{"df":1,"token":"rbwm-village-greens"}],"rbwm-":[{"df":3,"token":"rbwm-settlements"},{"df":1,"token":"rbwm-allotments"},{"df":1,"token":"rbwm-conservation-areas"},{"df":1,"token":"rbwm-employment-sites"},{"df":1,"token":"rbwm-new-housing-sites"},{"df":1,"token":"rbwm-owned-open-spaces"},{"df":1,"token":"rbwm-potential-development-sites"},{"df":1,"token":"rbwm-smoke-control-zones"},{"df":1,"token":"rbwm-village-greens"}],"rbwm-a":[{"df":1,"token":"rbwm-allotments"}],"rbwm-al":[{"df":1,"token":"rbwm-allotments"}],"rbwm-all":[{"df":1,"token":"rbwm-allotments"}],"rbwm-c":[{"df":1,"token":"rbwm-conservation-areas"}],"rbwm-co":[{"df":1,"token":"rbwm-conservation-areas"}],"rbwm-con":[{"df":1,"token":"rbwm-conservation-areas"}],"rbwm-e":[{"df":1,"token":"rbwm-employment-sites"}],"rbwm-em":[{"df":1,"token":"rbwm-employment-sites"}],"rbwm-emp":[{"df":1,"token":"rbwm-employment-sites"}],"rbwm-n":[{"df":1,"token":"rbwm-new-housing-sites"}],"rbwm-ne":[{"df":1,"token":"rbwm-new-housing-sites"}],"rbwm-new":[{"df":1,"token":"rbwm-new-housing-sites"}],"rbwm-o":[{"df":1,"token":"rbwm-owned-open-spaces"}],"rbwm-ow":[{"df":1,"token":"rbwm-owned-open-spaces"}],"rbwm-own":[{"df":1,"token":"rbwm-owned-open-spaces"}],"rbwm-p":[{"df":1,"token":"rbwm-potential-development-sites"}],"rbwm-po":[{"df":1,"token":"rbwm-potential-development-sites"}],"rbwm-pot":[{"df":1,"token":"rbwm-potential-development-sites"}],"rbwm-s":[{"df":3,"token":"rbwm-settlements"},{"df":1,"token":"rbwm-smoke-control-zones"}],"rbwm-se":[{"df":3,"token":"rbwm-settlements"}],"rbwm-set":[{"df":3,"token":"rbwm-settlements"}],"rbwm-sm":[{"df":1,"token":"rbwm-smoke-control-zones"}],"rbwm-smo":[{"df":1,"token":"rbwm-smoke-control-zones"}],"rbwm-v":[{"df":1,"token":"rbwm-village-greens"}],"rbwm-vi":[{"df":1,"token":"rbwm-village-greens"}],"rbwm-vil":[{"df":1,"token":"rbwm-village-greens"}]}
