{"tb-":[{"df":3,"token":"tb-c11"},{"df":3,"token":"tb-housing-allocations1"},{"df":3,"token":"tb-policy-s6-local-shopping-frontage1"},{"df":3,"token":"tb-ss1-ddb1"}],"tb-c":[{"df":3,"token":"tb-c11"}],"tb-c1":[{"df":3,"token":"tb-c11"}],"tb-c11":[{"df":3,"token":"tb-c11"}],"tb-h":[{"df":3,"token":"tb-housing-allocations1"}],"tb-ho":[{"df":3,"token":"tb-housing-allocations1"}],"tb-hou":[{"df":3,"token":"tb-housing-allocations1"}],"tb-hous":[{"df":3,"token":"tb-housing-allocations1"}],"tb-housi":[{"df":3,"token":"tb-housing-allocations1"}],"tb-p":[{"df":3,"token":"tb-policy-s6-local-shopping-frontage1"}],"tb-po":[{"df":3,"token":"tb-policy-s6-local-shopping-frontage1"}],"tb-pol":[{"df":3,"token":"tb-policy-s6-local-shopping-frontage1"}],"tb-poli":[{"df":3,"token":"tb-policy-s6-local-shopping-frontage1"}],"tb-polic":[{"df":3,"token":"tb-policy-s6-local-shopping-frontage1"}],"tb-s":[{"df":3,"token":"tb-ss1-ddb1"}],"tb-ss":[{"df":3,"token":"tb-ss1-ddb1"}],"tb-ss1":[{"df":3,"token":"tb-ss1-ddb1"}],"tb-ss1-":[{"df":3,"token":"tb-ss1-ddb1"}],"tb-ss1-d":[{"df":3,"token":"tb-ss1-ddb1"}],"tb_":[{"df":1,"token":"tb_c1"},{"df":1,"token":"tb_housing_allocations"},{"df":1,"token":"tb_policy_s6_local_shopping_frontage"}],"tb_c":[{"df":1,"token":"tb_c1"}],"tb_c1":[{"df":1,"token":"tb_c1"}],"tb_h":[{"df":1,"token":"tb_housing_allocations"}],"tb_ho":[{"df":1,"token":"tb_housing_allocations"}],"tb_hou":[{"df":1,"token":"tb_housing_allocations"}],"tb_hous":[{"df":1,"token":"tb_housing_allocations"}],"tb_housi":[{"df":1,"token":"tb_housing_allocations"}],"tb_p":[{"df":1,"token":"tb_policy_s6_local_shopping_frontage"}],"tb_po":[{"df":1,"token":"tb_policy_s6_local_shopping_frontage"}],"tb_pol":[{"df":1,"token":"tb_policy_s6_local_shopping_frontage"}],"tb_poli":[{"df":1,"token":"tb_policy_s6_local_shopping_frontage"}],"tb_polic":[{"df":1,"token":"tb_policy_s6_local_shopping_frontage"}],"tbc":[{"df":3,"token":"tbc"}],"tbh":[{"df":1,"token":"tbh"}],"tbr":[{"df":1,"token":"tbr"}]}
